ExBrainable/GUI.py
ExBrainable/__init__.py
ExBrainable/dataloader.py
ExBrainable/models.py
ExBrainable/scheme_var.py
ExBrainable/train_test.py
ExBrainable/variable.py
ExBrainable/visualization.py
ExBrainable-0.0.11.dist-info/LICENSE
ExBrainable-0.0.11.dist-info/METADATA
ExBrainable-0.0.11.dist-info/WHEEL
ExBrainable-0.0.11.dist-info/entry_points.txt
ExBrainable-0.0.11.dist-info/top_level.txt
ExBrainable-0.0.11.dist-info/RECORD
