Metadata-Version: 2.1
Name: ExBrainable
Version: 0.0.11
Summary: ExBrainable: An Open-Source GUI for CNN-based EEG Decoding and Model Interpretation
Home-page: https://github.com/CECNL/ExBrainable
Author: Ya-Lin Huang
Author-email: yalinhuang.bt06@nycu.edu.tw
Keywords: eeg deep-learning brain-state-decoding
Classifier: Intended Audience :: Developers
Classifier: Intended Audience :: Science/Research
Classifier: Topic :: Software Development :: Build Tools
Classifier: Topic :: Scientific/Engineering :: Artificial Intelligence
Classifier: License :: OSI Approved :: GNU General Public License v3 (GPLv3)
Classifier: Programming Language :: Python :: 3.7
License-File: LICENSE
Requires-Dist: mne
Requires-Dist: numpy
Requires-Dist: scipy
Requires-Dist: matplotlib
Requires-Dist: torchsummary
Requires-Dist: sklearn
